asvmq/__init__.py
asvmq/broadcaster.py
asvmq/topic_communications.py
asvmq-0.1.6.dist-info/METADATA
asvmq-0.1.6.dist-info/WHEEL
asvmq-0.1.6.dist-info/top_level.txt
asvmq-0.1.6.dist-info/zip-safe
asvmq-0.1.6.dist-info/RECORD
