Metadata-Version: 2.1
Name: asvmq
Version: 0.1.6
Summary: ASV Messaging Queue API for message passing between processes.
Home-page: https://github.com/akashp1997/asv_mq
Author: Akash Purandare
Author-email: akash.p1997@gmail.com
License: BSD-3-Clause
Keywords: asv_mq
Platform: UNKNOWN
Requires-Dist: asvprotobuf
Requires-Dist: pika
